{
  "rows": 62,
  "columns": [
    "id",
    "question",
    "answer",
    "category",
    "tags",
    "alt_questions",
    "img_keys",
    "entity_type"
  ],
  "nulls": {
    "id": 0,
    "question": 0,
    "answer": 0,
    "category": 0,
    "tags": 0,
    "alt_questions": 12,
    "img_keys": 54,
    "entity_type": 0
  },
  "empties": {
    "id": 0,
    "question": 0,
    "answer": 0,
    "category": 0,
    "tags": 0,
    "alt_questions": 12,
    "img_keys": 62,
    "entity_type": 0
  },
  "duplicate_id_rows": 0,
  "invalid_entity_type_rows": 0
}